<?xml version="1.0" encoding="ISO-8859-1"?>
<attributes>
<attribute>
<srcPos sline="0" eline="0" spos="0" epos="0"/>
<jmpPos sline="0" eline="0" spos="0" epos="0"/>
<text info="Signature: Landroid/support/v7/internal/view/menu/BaseWrapper&lt;Landroid/view/MenuItem$OnMenuItemClickListener;&gt;;Landroid/view/MenuItem$OnMenuItemClickListener;" aType="SignatureTag"/>
<text info="[inner=android/view/MenuItem$OnMenuItemClickListener, outer=android/view/MenuItem, name=OnMenuItemClickListener,flags=1545]" aType="InnerClassTag"/>
<text info="[inner=android/support/v7/internal/view/menu/MenuItemWrapperICS$OnMenuItemClickListenerWrapper, outer=android/support/v7/internal/view/menu/MenuItemWrapperICS, name=OnMenuItemClickListenerWrapper,flags=2]" aType="InnerClassTag"/>
<text info="soot.tagkit.InnerClassAttribute@8d5339c" aType="InnerClassAttribute"/>
</attribute>
</attributes>
