<?xml version="1.0" encoding="ISO-8859-1"?>
<attributes>
<attribute>
<srcPos sline="0" eline="0" spos="0" epos="0"/>
<jmpPos sline="0" eline="0" spos="0" epos="0"/>
<text info="Signature: &lt;K:Ljava/lang/Object;V1:Ljava/lang/Object;V2:Ljava/lang/Object;&gt;Ljava/util/AbstractMap&lt;TK;TV2;&gt;;" aType="SignatureTag"/>
<text info="[inner=com/google/common/collect/Maps$TransformedEntriesMap, outer=com/google/common/collect/Maps, name=TransformedEntriesMap,flags=8]" aType="InnerClassTag"/>
<text info="[inner=com/google/common/collect/Maps$TransformedEntriesMap$2, outer=null, name=null,flags=0]" aType="InnerClassTag"/>
<text info="[inner=com/google/common/collect/Maps$TransformedEntriesMap$1, outer=null, name=null,flags=0]" aType="InnerClassTag"/>
<text info="[inner=com/google/common/collect/Maps$EntryTransformer, outer=com/google/common/collect/Maps, name=EntryTransformer,flags=1545]" aType="InnerClassTag"/>
<text info="[inner=java/util/Map$Entry, outer=java/util/Map, name=Entry,flags=1545]" aType="InnerClassTag"/>
<text info="soot.tagkit.InnerClassAttribute@62de9d96" aType="InnerClassAttribute"/>
</attribute>
<attribute>
<srcPos sline="0" eline="0" spos="0" epos="0"/>
<jmpPos sline="3" eline="3" spos="0" epos="0"/>
<text info="Signature: Ljava/util/Map&lt;TK;TV1;&gt;;" aType="SignatureTag"/>
</attribute>
<attribute>
<srcPos sline="0" eline="0" spos="0" epos="0"/>
<jmpPos sline="4" eline="4" spos="0" epos="0"/>
<text info="Signature: Lcom/google/common/collect/Maps$EntryTransformer&lt;-TK;-TV1;TV2;&gt;;" aType="SignatureTag"/>
</attribute>
<attribute>
<srcPos sline="0" eline="0" spos="0" epos="0"/>
<jmpPos sline="5" eline="5" spos="0" epos="0"/>
<text info="Signature: Ljava/util/Set&lt;Ljava/util/Map$Entry&lt;TK;TV2;&gt;;&gt;;" aType="SignatureTag"/>
</attribute>
<attribute>
<srcPos sline="0" eline="0" spos="0" epos="0"/>
<jmpPos sline="6" eline="6" spos="0" epos="0"/>
<text info="Signature: Ljava/util/Collection&lt;TV2;&gt;;" aType="SignatureTag"/>
</attribute>
<attribute>
<srcPos sline="0" eline="0" spos="0" epos="0"/>
<jmpPos sline="8" eline="8" spos="0" epos="0"/>
<text info="Signature: (Ljava/util/Map&lt;TK;TV1;&gt;;Lcom/google/common/collect/Maps$EntryTransformer&lt;-TK;-TV1;TV2;&gt;;)V" aType="SignatureTag"/>
</attribute>
<attribute>
<srcPos sline="0" eline="0" spos="0" epos="0"/>
<jmpPos sline="71" eline="71" spos="0" epos="0"/>
<text info="Signature: (Ljava/lang/Object;)TV2;" aType="SignatureTag"/>
</attribute>
<attribute>
<srcPos sline="0" eline="0" spos="0" epos="0"/>
<jmpPos sline="109" eline="109" spos="0" epos="0"/>
<text info="Signature: (Ljava/lang/Object;)TV2;" aType="SignatureTag"/>
</attribute>
<attribute>
<srcPos sline="0" eline="0" spos="0" epos="0"/>
<jmpPos sline="158" eline="158" spos="0" epos="0"/>
<text info="Signature: ()Ljava/util/Set&lt;TK;&gt;;" aType="SignatureTag"/>
</attribute>
<attribute>
<srcPos sline="0" eline="0" spos="0" epos="0"/>
<jmpPos sline="173" eline="173" spos="0" epos="0"/>
<text info="Signature: ()Ljava/util/Set&lt;Ljava/util/Map$Entry&lt;TK;TV2;&gt;;&gt;;" aType="SignatureTag"/>
</attribute>
<attribute>
<srcPos sline="0" eline="0" spos="0" epos="0"/>
<jmpPos sline="197" eline="197" spos="0" epos="0"/>
<text info="Signature: ()Ljava/util/Collection&lt;TV2;&gt;;" aType="SignatureTag"/>
</attribute>
</attributes>
