<?xml version="1.0" encoding="ISO-8859-1"?>
<attributes>
<attribute>
<srcPos sline="0" eline="0" spos="0" epos="0"/>
<jmpPos sline="0" eline="0" spos="0" epos="0"/>
<text info="Signature: Lcom/google/common/collect/Multimaps$Values&lt;TK;TV;&gt;;" aType="SignatureTag"/>
<text info="[inner=com/google/common/collect/Multimaps$FilteredMultimap, outer=com/google/common/collect/Multimaps, name=FilteredMultimap,flags=10]" aType="InnerClassTag"/>
<text info="[inner=com/google/common/collect/Multimaps$FilteredMultimap$Values, outer=com/google/common/collect/Multimaps$FilteredMultimap, name=Values,flags=0]" aType="InnerClassTag"/>
<text info="[inner=java/util/Map$Entry, outer=java/util/Map, name=Entry,flags=1545]" aType="InnerClassTag"/>
<text info="[inner=com/google/common/collect/Multimaps$Values, outer=com/google/common/collect/Multimaps, name=Values,flags=1032]" aType="InnerClassTag"/>
<text info="soot.tagkit.InnerClassAttribute@27b19f56" aType="InnerClassAttribute"/>
</attribute>
<attribute>
<srcPos sline="0" eline="0" spos="0" epos="0"/>
<jmpPos sline="21" eline="21" spos="0" epos="0"/>
<text info="Signature: ()Lcom/google/common/collect/Multimap&lt;TK;TV;&gt;;" aType="SignatureTag"/>
</attribute>
<attribute>
<srcPos sline="0" eline="0" spos="0" epos="0"/>
<jmpPos sline="33" eline="33" spos="0" epos="0"/>
<text info="Visibility Param Annotation: num params: 1 kind: 0
Visibility Annotation: level: RUNTIME (runtime-visible)
 Annotations:
Annotation type: Ljavax/annotation/Nullable; without elements

" aType="VisibilityParameterAnnotationTag"/>
</attribute>
<attribute>
<srcPos sline="0" eline="0" spos="0" epos="0"/>
<jmpPos sline="109" eline="109" spos="0" epos="0"/>
<text info="Signature: (Ljava/util/Collection&lt;*&gt;;)Z" aType="SignatureTag"/>
</attribute>
<attribute>
<srcPos sline="0" eline="0" spos="0" epos="0"/>
<jmpPos sline="169" eline="169" spos="0" epos="0"/>
<text info="Signature: (Ljava/util/Collection&lt;*&gt;;)Z" aType="SignatureTag"/>
</attribute>
</attributes>
