<?xml version="1.0" encoding="ISO-8859-1"?>
<attributes>
<attribute>
<srcPos sline="0" eline="0" spos="0" epos="0"/>
<jmpPos sline="0" eline="0" spos="0" epos="0"/>
<text info="[inner=com/android/internal/widget/multiwaveview/Ease$Sine, outer=com/android/internal/widget/multiwaveview/Ease, name=Sine,flags=8]" aType="InnerClassTag"/>
<text info="[inner=com/android/internal/widget/multiwaveview/Ease$Quint, outer=com/android/internal/widget/multiwaveview/Ease, name=Quint,flags=8]" aType="InnerClassTag"/>
<text info="[inner=com/android/internal/widget/multiwaveview/Ease$Quart, outer=com/android/internal/widget/multiwaveview/Ease, name=Quart,flags=8]" aType="InnerClassTag"/>
<text info="[inner=com/android/internal/widget/multiwaveview/Ease$Quad, outer=com/android/internal/widget/multiwaveview/Ease, name=Quad,flags=8]" aType="InnerClassTag"/>
<text info="[inner=com/android/internal/widget/multiwaveview/Ease$Cubic, outer=com/android/internal/widget/multiwaveview/Ease, name=Cubic,flags=8]" aType="InnerClassTag"/>
<text info="[inner=com/android/internal/widget/multiwaveview/Ease$Linear, outer=com/android/internal/widget/multiwaveview/Ease, name=Linear,flags=8]" aType="InnerClassTag"/>
<text info="soot.tagkit.InnerClassAttribute@16c7e483" aType="InnerClassAttribute"/>
</attribute>
<attribute>
<srcPos sline="0" eline="0" spos="0" epos="0"/>
<jmpPos sline="3" eline="3" spos="0" epos="0"/>
<text info="ConstantValue: 1.0" aType="FloatConstantValueTag"/>
</attribute>
<attribute>
<srcPos sline="0" eline="0" spos="0" epos="0"/>
<jmpPos sline="4" eline="4" spos="0" epos="0"/>
<text info="ConstantValue: 1.0" aType="FloatConstantValueTag"/>
</attribute>
<attribute>
<srcPos sline="0" eline="0" spos="0" epos="0"/>
<jmpPos sline="5" eline="5" spos="0" epos="0"/>
<text info="ConstantValue: 0.0" aType="FloatConstantValueTag"/>
</attribute>
</attributes>
