<?xml version="1.0" encoding="ISO-8859-1"?>
<attributes>
<attribute>
<srcPos sline="0" eline="0" spos="0" epos="0"/>
<jmpPos sline="0" eline="0" spos="0" epos="0"/>
<text info="Signature: Ljava/lang/Object;Lcom/android/gallery3d/util/ThreadPool$Job&lt;Ljava/io/File;&gt;;Lcom/android/gallery3d/util/FutureListener&lt;Ljava/io/File;&gt;;" aType="SignatureTag"/>
<text info="[inner=com/android/gallery3d/data/DownloadCache$TaskProxy, outer=com/android/gallery3d/data/DownloadCache, name=TaskProxy,flags=9]" aType="InnerClassTag"/>
<text info="[inner=com/android/gallery3d/data/DownloadCache$DownloadTask, outer=com/android/gallery3d/data/DownloadCache, name=DownloadTask,flags=2]" aType="InnerClassTag"/>
<text info="[inner=com/android/gallery3d/data/DownloadCache$Entry, outer=com/android/gallery3d/data/DownloadCache, name=Entry,flags=1]" aType="InnerClassTag"/>
<text info="[inner=com/android/gallery3d/util/ThreadPool$JobContext, outer=com/android/gallery3d/util/ThreadPool, name=JobContext,flags=1545]" aType="InnerClassTag"/>
<text info="[inner=com/android/gallery3d/util/ThreadPool$Job, outer=com/android/gallery3d/util/ThreadPool, name=Job,flags=1545]" aType="InnerClassTag"/>
<text info="soot.tagkit.InnerClassAttribute@311a7399" aType="InnerClassAttribute"/>
</attribute>
<attribute>
<srcPos sline="0" eline="0" spos="0" epos="0"/>
<jmpPos sline="3" eline="3" spos="0" epos="0"/>
<text info="Signature: Ljava/util/HashSet&lt;Lcom/android/gallery3d/data/DownloadCache$TaskProxy;&gt;;" aType="SignatureTag"/>
</attribute>
<attribute>
<srcPos sline="0" eline="0" spos="0" epos="0"/>
<jmpPos sline="4" eline="4" spos="0" epos="0"/>
<text info="Signature: Lcom/android/gallery3d/util/Future&lt;Ljava/io/File;&gt;;" aType="SignatureTag"/>
</attribute>
<attribute>
<srcPos sline="0" eline="0" spos="0" epos="0"/>
<jmpPos sline="132" eline="132" spos="0" epos="0"/>
<text info="Signature: (Lcom/android/gallery3d/util/Future&lt;Ljava/io/File;&gt;;)V" aType="SignatureTag"/>
</attribute>
</attributes>
