<?xml version="1.0" encoding="ISO-8859-1"?>
<attributes>
<attribute>
<srcPos sline="0" eline="0" spos="0" epos="0"/>
<jmpPos sline="0" eline="0" spos="0" epos="0"/>
<text info="Enclosing Class: com/android/inputmethod/keyboard/emoji/EmojiPalettesView$DeleteKeyOnTouchListener Enclosing Method: &lt;init&gt; Sig: (Landroid/content/Context;)V" aType="EnclosingMethodTag"/>
<text info="[inner=com/android/inputmethod/keyboard/emoji/EmojiPalettesView$DeleteKeyOnTouchListener, outer=com/android/inputmethod/keyboard/emoji/EmojiPalettesView, name=DeleteKeyOnTouchListener,flags=10]" aType="InnerClassTag"/>
<text info="[inner=com/android/inputmethod/keyboard/emoji/EmojiPalettesView$DeleteKeyOnTouchListener$1, outer=null, name=null,flags=0]" aType="InnerClassTag"/>
<text info="soot.tagkit.InnerClassAttribute@22f4a8f6" aType="InnerClassAttribute"/>
</attribute>
</attributes>
