<?xml version="1.0" encoding="ISO-8859-1"?>
<attributes>
<attribute>
<srcPos sline="0" eline="0" spos="0" epos="0"/>
<jmpPos sline="7" eline="7" spos="0" epos="0"/>
<text info="Signature: Ljava/util/List&lt;Ljava/lang/String;&gt;;" aType="SignatureTag"/>
</attribute>
<attribute>
<srcPos sline="0" eline="0" spos="0" epos="0"/>
<jmpPos sline="11" eline="11" spos="0" epos="0"/>
<text info="Signature: (Ljava/lang/String;ILjavax/net/ssl/SSLSocketFactory;Ljavax/net/ssl/HostnameVerifier;Lcom/android/okhttp/OkAuthenticator;Ljava/net/Proxy;Ljava/util/List&lt;Ljava/lang/String;&gt;;)V" aType="SignatureTag"/>
</attribute>
<attribute>
<srcPos sline="0" eline="0" spos="0" epos="0"/>
<jmpPos sline="255" eline="255" spos="0" epos="0"/>
<text info="Signature: ()Ljava/util/List&lt;Ljava/lang/String;&gt;;" aType="SignatureTag"/>
</attribute>
</attributes>
