<?xml version="1.0" encoding="ISO-8859-1"?>
<attributes>
<attribute>
<srcPos sline="0" eline="0" spos="0" epos="0"/>
<jmpPos sline="24" eline="24" spos="0" epos="0"/>
<text info="Signature: &lt;T:Ljava/lang/Object;&gt;(Ljava/security/PrivilegedAction&lt;TT;&gt;;)TT;" aType="SignatureTag"/>
</attribute>
<attribute>
<srcPos sline="0" eline="0" spos="0" epos="0"/>
<jmpPos sline="36" eline="36" spos="0" epos="0"/>
<text info="Signature: &lt;T:Ljava/lang/Object;&gt;(Ljava/security/PrivilegedAction&lt;TT;&gt;;Ljava/security/AccessControlContext;)TT;" aType="SignatureTag"/>
</attribute>
<attribute>
<srcPos sline="0" eline="0" spos="0" epos="0"/>
<jmpPos sline="51" eline="51" spos="0" epos="0"/>
<text info="Signature: &lt;T:Ljava/lang/Object;&gt;(Ljava/security/PrivilegedExceptionAction&lt;TT;&gt;;)TT;" aType="SignatureTag"/>
</attribute>
<attribute>
<srcPos sline="0" eline="0" spos="0" epos="0"/>
<jmpPos sline="89" eline="89" spos="0" epos="0"/>
<text info="Signature: &lt;T:Ljava/lang/Object;&gt;(Ljava/security/PrivilegedExceptionAction&lt;TT;&gt;;Ljava/security/AccessControlContext;)TT;" aType="SignatureTag"/>
</attribute>
<attribute>
<srcPos sline="0" eline="0" spos="0" epos="0"/>
<jmpPos sline="104" eline="104" spos="0" epos="0"/>
<text info="Signature: &lt;T:Ljava/lang/Object;&gt;(Ljava/security/PrivilegedAction&lt;TT;&gt;;)TT;" aType="SignatureTag"/>
</attribute>
<attribute>
<srcPos sline="0" eline="0" spos="0" epos="0"/>
<jmpPos sline="116" eline="116" spos="0" epos="0"/>
<text info="Signature: &lt;T:Ljava/lang/Object;&gt;(Ljava/security/PrivilegedExceptionAction&lt;TT;&gt;;)TT;" aType="SignatureTag"/>
</attribute>
</attributes>
