<?xml version="1.0" encoding="ISO-8859-1"?>
<attributes>
<attribute>
<srcPos sline="0" eline="0" spos="0" epos="0"/>
<jmpPos sline="0" eline="0" spos="0" epos="0"/>
<text info="Signature: &lt;E:Ljava/lang/Object;&gt;Ljava/lang/Object;" aType="SignatureTag"/>
<text info="[inner=com/android/camera/util/ConcurrentSharedRingBuffer$Pinnable, outer=com/android/camera/util/ConcurrentSharedRingBuffer, name=Pinnable,flags=10]" aType="InnerClassTag"/>
<text info="[inner=com/android/camera/util/ConcurrentSharedRingBuffer$PinStateListener, outer=com/android/camera/util/ConcurrentSharedRingBuffer, name=PinStateListener,flags=1545]" aType="InnerClassTag"/>
<text info="[inner=com/android/camera/util/ConcurrentSharedRingBuffer$Selector, outer=com/android/camera/util/ConcurrentSharedRingBuffer, name=Selector,flags=1545]" aType="InnerClassTag"/>
<text info="[inner=com/android/camera/util/ConcurrentSharedRingBuffer$SwapTask, outer=com/android/camera/util/ConcurrentSharedRingBuffer, name=SwapTask,flags=1545]" aType="InnerClassTag"/>
<text info="[inner=com/android/camera/util/ConcurrentSharedRingBuffer$1, outer=null, name=null,flags=0]" aType="InnerClassTag"/>
<text info="[inner=com/android/camera/debug/Log$Tag, outer=com/android/camera/debug/Log, name=Tag,flags=25]" aType="InnerClassTag"/>
<text info="[inner=java/util/Map$Entry, outer=java/util/Map, name=Entry,flags=1545]" aType="InnerClassTag"/>
<text info="soot.tagkit.InnerClassAttribute@42612bd2" aType="InnerClassAttribute"/>
</attribute>
<attribute>
<srcPos sline="0" eline="0" spos="0" epos="0"/>
<jmpPos sline="6" eline="6" spos="0" epos="0"/>
<text info="Signature: Ljava/util/TreeMap&lt;Ljava/lang/Long;Lcom/android/camera/util/ConcurrentSharedRingBuffer$Pinnable&lt;TE;&gt;;&gt;;" aType="SignatureTag"/>
</attribute>
<attribute>
<srcPos sline="0" eline="0" spos="0" epos="0"/>
<jmpPos sline="7" eline="7" spos="0" epos="0"/>
<text info="Signature: Ljava/util/TreeMap&lt;Ljava/lang/Long;Lcom/android/camera/util/ConcurrentSharedRingBuffer$Pinnable&lt;TE;&gt;;&gt;;" aType="SignatureTag"/>
</attribute>
<attribute>
<srcPos sline="0" eline="0" spos="0" epos="0"/>
<jmpPos sline="130" eline="130" spos="0" epos="0"/>
<text info="Signature: (JLcom/android/camera/util/ConcurrentSharedRingBuffer$SwapTask&lt;TE;&gt;;)Z" aType="SignatureTag"/>
</attribute>
<attribute>
<srcPos sline="0" eline="0" spos="0" epos="0"/>
<jmpPos sline="512" eline="512" spos="0" epos="0"/>
<text info="Signature: (J)Landroid/util/Pair&lt;Ljava/lang/Long;TE;&gt;;" aType="SignatureTag"/>
</attribute>
<attribute>
<srcPos sline="0" eline="0" spos="0" epos="0"/>
<jmpPos sline="763" eline="763" spos="0" epos="0"/>
<text info="Signature: ()Landroid/util/Pair&lt;Ljava/lang/Long;TE;&gt;;" aType="SignatureTag"/>
</attribute>
<attribute>
<srcPos sline="0" eline="0" spos="0" epos="0"/>
<jmpPos sline="836" eline="836" spos="0" epos="0"/>
<text info="Signature: (Lcom/android/camera/util/ConcurrentSharedRingBuffer$Selector&lt;TE;&gt;;)Landroid/util/Pair&lt;Ljava/lang/Long;TE;&gt;;" aType="SignatureTag"/>
</attribute>
<attribute>
<srcPos sline="0" eline="0" spos="0" epos="0"/>
<jmpPos sline="991" eline="991" spos="0" epos="0"/>
<text info="Signature: (Lcom/android/camera/util/Task&lt;TE;&gt;;)V" aType="SignatureTag"/>
</attribute>
</attributes>
