<?xml version="1.0" encoding="ISO-8859-1"?>
<attributes>
<attribute>
<srcPos sline="0" eline="0" spos="0" epos="0"/>
<jmpPos sline="0" eline="0" spos="0" epos="0"/>
<text info="[inner=com/android/server/accessibility/AccessibilityManagerService$UserState, outer=com/android/server/accessibility/AccessibilityManagerService, name=UserState,flags=2]" aType="InnerClassTag"/>
<text info="[inner=com/android/server/accessibility/AccessibilityManagerService$UserState$1, outer=null, name=null,flags=0]" aType="InnerClassTag"/>
<text info="soot.tagkit.InnerClassAttribute@4a8e3a4d" aType="InnerClassAttribute"/>
</attribute>
<attribute>
<srcPos sline="0" eline="0" spos="0" epos="0"/>
<jmpPos sline="3" eline="3" spos="0" epos="0"/>
<text info="Signature: Ljava/util/Set&lt;Landroid/content/ComponentName;&gt;;" aType="SignatureTag"/>
</attribute>
<attribute>
<srcPos sline="0" eline="0" spos="0" epos="0"/>
<jmpPos sline="4" eline="4" spos="0" epos="0"/>
<text info="Signature: Ljava/util/concurrent/CopyOnWriteArrayList&lt;Lcom/android/server/accessibility/AccessibilityManagerService$Service;&gt;;" aType="SignatureTag"/>
</attribute>
<attribute>
<srcPos sline="0" eline="0" spos="0" epos="0"/>
<jmpPos sline="5" eline="5" spos="0" epos="0"/>
<text info="Signature: Landroid/os/RemoteCallbackList&lt;Landroid/view/accessibility/IAccessibilityManagerClient;&gt;;" aType="SignatureTag"/>
</attribute>
<attribute>
<srcPos sline="0" eline="0" spos="0" epos="0"/>
<jmpPos sline="6" eline="6" spos="0" epos="0"/>
<text info="Signature: Ljava/util/Map&lt;Landroid/content/ComponentName;Lcom/android/server/accessibility/AccessibilityManagerService$Service;&gt;;" aType="SignatureTag"/>
</attribute>
<attribute>
<srcPos sline="0" eline="0" spos="0" epos="0"/>
<jmpPos sline="7" eline="7" spos="0" epos="0"/>
<text info="Signature: Ljava/util/Set&lt;Landroid/content/ComponentName;&gt;;" aType="SignatureTag"/>
</attribute>
<attribute>
<srcPos sline="0" eline="0" spos="0" epos="0"/>
<jmpPos sline="9" eline="9" spos="0" epos="0"/>
<text info="Signature: Ljava/util/List&lt;Landroid/accessibilityservice/AccessibilityServiceInfo;&gt;;" aType="SignatureTag"/>
</attribute>
<attribute>
<srcPos sline="0" eline="0" spos="0" epos="0"/>
<jmpPos sline="10" eline="10" spos="0" epos="0"/>
<text info="Signature: Landroid/util/SparseArray&lt;Lcom/android/server/accessibility/AccessibilityManagerService$AccessibilityConnectionWrapper;&gt;;" aType="SignatureTag"/>
</attribute>
<attribute>
<srcPos sline="0" eline="0" spos="0" epos="0"/>
<jmpPos sline="17" eline="17" spos="0" epos="0"/>
<text info="Signature: Ljava/util/Set&lt;Landroid/content/ComponentName;&gt;;" aType="SignatureTag"/>
</attribute>
<attribute>
<srcPos sline="0" eline="0" spos="0" epos="0"/>
<jmpPos sline="23" eline="23" spos="0" epos="0"/>
<text info="Signature: Landroid/util/SparseArray&lt;Landroid/os/IBinder;&gt;;" aType="SignatureTag"/>
</attribute>
</attributes>
