<?xml version="1.0" encoding="ISO-8859-1"?>
<attributes>
<attribute>
<srcPos sline="0" eline="0" spos="0" epos="0"/>
<jmpPos sline="3" eline="3" spos="0" epos="0"/>
<text info="ConstantValue: fix_parent_keys" aType="StringConstantValueTag"/>
</attribute>
<attribute>
<srcPos sline="0" eline="0" spos="0" epos="0"/>
<jmpPos sline="4" eline="4" spos="0" epos="0"/>
<text info="ConstantValue: (parentKey isnull OR parentKey=0)" aType="StringConstantValueTag"/>
</attribute>
<attribute>
<srcPos sline="0" eline="0" spos="0" epos="0"/>
<jmpPos sline="5" eline="5" spos="0" epos="0"/>
<text info="ConstantValue: 512" aType="IntegerConstantValueTag"/>
</attribute>
<attribute>
<srcPos sline="0" eline="0" spos="0" epos="0"/>
<jmpPos sline="7" eline="7" spos="0" epos="0"/>
<text info="ConstantValue: 0" aType="IntegerConstantValueTag"/>
</attribute>
<attribute>
<srcPos sline="0" eline="0" spos="0" epos="0"/>
<jmpPos sline="8" eline="8" spos="0" epos="0"/>
<text info="ConstantValue: 1" aType="IntegerConstantValueTag"/>
</attribute>
<attribute>
<srcPos sline="0" eline="0" spos="0" epos="0"/>
<jmpPos sline="9" eline="9" spos="0" epos="0"/>
<text info="ConstantValue: 2" aType="IntegerConstantValueTag"/>
</attribute>
<attribute>
<srcPos sline="0" eline="0" spos="0" epos="0"/>
<jmpPos sline="10" eline="10" spos="0" epos="0"/>
<text info="ConstantValue: 3" aType="IntegerConstantValueTag"/>
</attribute>
<attribute>
<srcPos sline="0" eline="0" spos="0" epos="0"/>
<jmpPos sline="23" eline="23" spos="0" epos="0"/>
<text info="Visibility Annotation: level: RUNTIME (runtime-visible)
 Annotations:
Annotation type: Ljava/lang/Deprecated; without elements
" aType="VisibilityAnnotationTag"/>
</attribute>
<attribute>
<srcPos sline="0" eline="0" spos="0" epos="0"/>
<jmpPos sline="196" eline="196" spos="0" epos="0"/>
<text info="Visibility Annotation: level: RUNTIME (runtime-visible)
 Annotations:
Annotation type: Ljava/lang/Deprecated; without elements
" aType="VisibilityAnnotationTag"/>
</attribute>
<attribute>
<srcPos sline="0" eline="0" spos="0" epos="0"/>
<jmpPos sline="269" eline="269" spos="0" epos="0"/>
<text info="Visibility Annotation: level: RUNTIME (runtime-visible)
 Annotations:
Annotation type: Ljava/lang/Deprecated; without elements
" aType="VisibilityAnnotationTag"/>
</attribute>
<attribute>
<srcPos sline="0" eline="0" spos="0" epos="0"/>
<jmpPos sline="461" eline="461" spos="0" epos="0"/>
<text info="Visibility Annotation: level: RUNTIME (runtime-visible)
 Annotations:
Annotation type: Ljava/lang/Deprecated; without elements
" aType="VisibilityAnnotationTag"/>
</attribute>
<attribute>
<srcPos sline="0" eline="0" spos="0" epos="0"/>
<jmpPos sline="548" eline="548" spos="0" epos="0"/>
<text info="Signature: (Landroid/content/Context;JLjava/util/HashMap&lt;Ljava/lang/Long;Ljava/lang/String;&gt;;Ljava/lang/String;J)Ljava/lang/String;" aType="SignatureTag"/>
</attribute>
</attributes>
